README.md
setup.py
mariasql/MariaSQL.py
mariasql/__init__.py
mariasql.egg-info/PKG-INFO
mariasql.egg-info/SOURCES.txt
mariasql.egg-info/dependency_links.txt
mariasql.egg-info/not-zip-safe
mariasql.egg-info/requires.txt
mariasql.egg-info/top_level.txt