Metadata-Version: 1.0
Name: mariasql
Version: 1
Summary: MariaDB/MySQL query builder primary for inserting and updating Python dictionaries into tables.
Home-page: https://git.osuv.de/m/mariasql
Author: Markus Bergholz
Author-email: markuman@gmail.com
License: WTFPL
Platform: UNKNOWN
